{ "height":16,
 "layers":[
        {
         "data":[44, 44, 44, 44, 44, 78, 1, 2, 1, 2, 73, 44, 44, 44, 44, 44, 44, 114, 91, 90, 91, 94, 17, 18, 17, 18, 89, 90, 91, 90, 115, 44, 44, 46, 111, 112, 109, 110, 1, 2, 1, 2, 105, 106, 111, 112, 41, 44, 44, 62, 127, 128, 125, 126, 5, 6, 1, 2, 121, 122, 127, 128, 57, 44, 93, 94, 143, 144, 141, 142, 21, 22, 17, 18, 137, 138, 143, 144, 89, 90, 109, 110, 159, 160, 157, 158, 17, 18, 17, 18, 153, 154, 159, 160, 105, 106, 125, 126, 1, 2, 1, 2, 1, 2, 1, 2, 1, 2, 1, 2, 121, 122, 141, 142, 17, 18, 17, 18, 17, 18, 17, 18, 17, 18, 17, 18, 137, 138, 157, 158, 1, 2, 1, 2, 1, 2, 1, 2, 1, 2, 1, 2, 153, 154, 1, 2, 17, 18, 17, 18, 17, 18, 17, 18, 17, 18, 17, 18, 1, 2, 1, 2, 1, 2, 1, 2, 1, 2, 1, 2, 1, 2, 1, 2, 1, 2, 17, 18, 17, 18, 17, 18, 17, 18, 17, 18, 17, 18, 17, 18, 17, 18, 1, 2, 1, 2, 1, 2, 1, 2, 1, 2, 1, 2, 1, 2, 1, 2, 13, 14, 17, 18, 17, 18, 17, 18, 17, 18, 17, 18, 17, 18, 9, 10, 29, 30, 1, 2, 1, 2, 1, 2, 1, 2, 1, 2, 1, 2, 25, 26, 45, 130, 10, 11, 12, 13, 10, 11, 12, 13, 10, 11, 12, 13, 131, 42],
         "height":16,
         "name":"PlaneA",
         "opacity":1,
         "type":"tilelayer",
         "visible":true,
         "width":16,
         "x":0,
         "y":0
        }, 
        {
         "color":"#00ff00",
         "draworder":"topdown",
         "name":"Collision",
         "objects":[
                {
                 "height":8,
                 "id":21,
                 "name":"",
                 "rotation":0,
                 "type":"",
                 "visible":true,
                 "width":40,
                 "x":8,
                 "y":24
                }, 
                {
                 "height":24,
                 "id":22,
                 "name":"",
                 "rotation":0,
                 "type":"",
                 "visible":true,
                 "width":8,
                 "x":40,
                 "y":0
                }, 
                {
                 "height":8,
                 "id":23,
                 "name":"",
                 "rotation":0,
                 "type":"",
                 "visible":true,
                 "width":16,
                 "x":0,
                 "y":48
                }, 
                {
                 "height":16,
                 "id":24,
                 "name":"",
                 "rotation":0,
                 "type":"",
                 "visible":true,
                 "width":8,
                 "x":8,
                 "y":32
                }, 
                {
                 "height":24,
                 "id":25,
                 "name":"",
                 "rotation":0,
                 "type":"",
                 "visible":true,
                 "width":8,
                 "x":80,
                 "y":0
                }, 
                {
                 "height":8,
                 "id":26,
                 "name":"",
                 "rotation":0,
                 "type":"",
                 "visible":true,
                 "width":40,
                 "x":80,
                 "y":24
                }, 
                {
                 "height":8,
                 "id":27,
                 "name":"",
                 "rotation":0,
                 "type":"",
                 "visible":true,
                 "width":16,
                 "x":112,
                 "y":48
                }, 
                {
                 "height":16,
                 "id":28,
                 "name":"",
                 "rotation":0,
                 "type":"",
                 "visible":true,
                 "width":8,
                 "x":112,
                 "y":32
                }, 
                {
                 "height":8,
                 "id":29,
                 "name":"",
                 "rotation":0,
                 "type":"",
                 "visible":true,
                 "width":16,
                 "x":0,
                 "y":104
                }, 
                {
                 "height":16,
                 "id":31,
                 "name":"",
                 "rotation":0,
                 "type":"",
                 "visible":true,
                 "width":8,
                 "x":8,
                 "y":112
                }, 
                {
                 "height":8,
                 "id":32,
                 "name":"",
                 "rotation":0,
                 "type":"",
                 "visible":true,
                 "width":96,
                 "x":16,
                 "y":120
                }, 
                {
                 "height":8,
                 "id":33,
                 "name":"",
                 "rotation":0,
                 "type":"",
                 "visible":true,
                 "width":16,
                 "x":112,
                 "y":104
                }, 
                {
                 "height":16,
                 "id":34,
                 "name":"",
                 "rotation":0,
                 "type":"",
                 "visible":true,
                 "width":8,
                 "x":112,
                 "y":112
                }],
         "opacity":1,
         "type":"objectgroup",
         "visible":true,
         "x":0,
         "y":0
        }, 
        {
         "color":"#640064",
         "draworder":"topdown",
         "name":"Warp",
         "objects":[
                {
                 "height":48,
                 "id":35,
                 "name":"",
                 "properties":
                    {
                     "target_room":1,
                     "target_room_spawn_x":340,
                     "target_room_spawn_y":142
                    },
                 "propertytypes":
                    {
                     "target_room":"int",
                     "target_room_spawn_x":"int",
                     "target_room_spawn_y":"int"
                    },
                 "rotation":0,
                 "type":"",
                 "visible":true,
                 "width":8,
                 "x":0,
                 "y":56
                }, 
                {
                 "height":8,
                 "id":36,
                 "name":"",
                 "properties":
                    {
                     "target_room":2,
                     "target_room_spawn_x":0,
                     "target_room_spawn_y":0
                    },
                 "propertytypes":
                    {
                     "target_room":"int",
                     "target_room_spawn_x":"int",
                     "target_room_spawn_y":"int"
                    },
                 "rotation":0,
                 "type":"",
                 "visible":true,
                 "width":32,
                 "x":48,
                 "y":0
                }, 
                {
                 "height":48,
                 "id":38,
                 "name":"",
                 "properties":
                    {
                     "target_room":3,
                     "target_room_spawn_x":0,
                     "target_room_spawn_y":0
                    },
                 "propertytypes":
                    {
                     "target_room":"int",
                     "target_room_spawn_x":"int",
                     "target_room_spawn_y":"int"
                    },
                 "rotation":0,
                 "type":"",
                 "visible":true,
                 "width":8,
                 "x":120,
                 "y":56
                }],
         "opacity":1,
         "type":"objectgroup",
         "visible":true,
         "x":0,
         "y":0
        }],
 "nextobjectid":41,
 "orientation":"orthogonal",
 "properties":
    {
     "map_name":"rabbibis_den_room_1",
     "spawn_x":56,
     "spawn_y":65,
     "tileset_name":"rabbibisden_tiles_def",
     "tileset_palette":"rabbibisden_tiles_pal_def"
    },
 "propertytypes":
    {
     "map_name":"string",
     "spawn_x":"int",
     "spawn_y":"int",
     "tileset_name":"string",
     "tileset_palette":"string"
    },
 "renderorder":"left-down",
 "tiledversion":"1.0.2",
 "tileheight":8,
 "tilesets":[
        {
         "firstgid":1,
         "source":"..\/..\/rabbibis_den_tileset.tsx"
        }],
 "tilewidth":8,
 "type":"map",
 "version":1,
 "width":16
}